README.md
setup.py
bankster/__init__.py
bankster.egg-info/PKG-INFO
bankster.egg-info/SOURCES.txt
bankster.egg-info/dependency_links.txt
bankster.egg-info/requires.txt
bankster.egg-info/top_level.txt
bankster/credstore/__init__.py
bankster/credstore/keepass.py
bankster/plugins/__init__.py
bankster/plugins/pl_bosbank24.py
bankster/plugins/pl_generali.py
bankster/plugins/pl_ideabank.py
bankster/plugins/pl_mbank.py
bankster/plugins/pl_nestbank.py
bankster/plugins/pl_obligacjeskarbowe.py
bankster/plugins/pl_starfunds.py