Metadata-Version: 2.1
Name: bankster
Version: 0.0.4
Summary: Access information from financial institutions
Home-page: https://github.com/mgrela/bankster
Author: Maciej Grela
Author-email: enki@fsck.pl
License: UNKNOWN
Platform: UNKNOWN
Classifier: Programming Language :: Python :: 3
Classifier: License :: OSI Approved :: GNU General Public License v3 (GPLv3)
Classifier: Operating System :: OS Independent
Classifier: Development Status :: 3 - Alpha
Classifier: Topic :: Office/Business :: Financial
Requires-Python: >=3.7
